professor_assistant2401138/__init__.py
professor_assistant2401138/fileHandler.py
professor_assistant2401138/interaction.py
professor_assistant2401138/main.py
professor_assistant2401138/qsnCreator.py
professor_assistant2401138-0.1.0.dist-info/LICENSE.txt
professor_assistant2401138-0.1.0.dist-info/METADATA
professor_assistant2401138-0.1.0.dist-info/WHEEL
professor_assistant2401138-0.1.0.dist-info/entry_points.txt
professor_assistant2401138-0.1.0.dist-info/top_level.txt
professor_assistant2401138-0.1.0.dist-info/RECORD
