Metadata-Version: 2.1
Name: professor-assistant2401138
Version: 0.1.0
Summary: A Python package to generate exams from question banks for professors.
Author: sabin
Author-email: sabin <sabin@dsu.ac.kr>
License: MIT
Classifier: Programming Language :: Python :: 3
Classifier: License :: OSI Approved :: MIT License
Classifier: Operating System :: OS Independent
Requires-Python: >=3.6
License-File: LICENSE.txt
